pyvmo/__init__.py
pyvmo/cli.py
pyvmo/format.py
pyvmo/operation.py
pyvmo/versions.py
pyvmo/vmo.py
pyvmo/distance/__init__.py
pyvmo/distance/ibs.py
pyVMO-0.0.7.dist-info/LICENSE
pyVMO-0.0.7.dist-info/METADATA
pyVMO-0.0.7.dist-info/WHEEL
pyVMO-0.0.7.dist-info/entry_points.txt
pyVMO-0.0.7.dist-info/top_level.txt
pyVMO-0.0.7.dist-info/RECORD
